CHANGES.txt
MANIFEST.in
README.txt
setup.py
js/__init__.py
js.jquery_kinetic.egg-info/PKG-INFO
js.jquery_kinetic.egg-info/SOURCES.txt
js.jquery_kinetic.egg-info/dependency_links.txt
js.jquery_kinetic.egg-info/entry_points.txt
js.jquery_kinetic.egg-info/namespace_packages.txt
js.jquery_kinetic.egg-info/not-zip-safe
js.jquery_kinetic.egg-info/requires.txt
js.jquery_kinetic.egg-info/top_level.txt
js/jquery_kinetic/__init__.py
js/jquery_kinetic/test_kinetic.txt
js/jquery_kinetic/resources/jquery.kinetic.js
js/jquery_kinetic/resources/jquery.kinetic.min.js