Metadata-Version: 1.0
Name: js.jquery-kinetic
Version: 1.8.2
Summary: fanstatic packaging of jquery.kinetic
Home-page: http://davetayls.me/jquery.kinetic/
Author: Sebastien Douche
Author-email: sdouche@gmail.com
License: BSD
Keywords: fanstatic,jquery,javascript
Platform: UNKNOWN
